{
    "ok": true,
    "data": {
        "objects": [
            {
                "objectId": "a5ddcc19-8dea-46ec-a2a0-a25bc9207934",
                "objectName": "Единица хранения АБДД",
                "versionId": null,
                "creator": "admin",
                "modifier": "system",
                "creationDate": "2022-06-23T12:58:35.983845",
                "modifyDate": "2022-07-04T12:49:24.793571",
                "objectState": null,
                "acl": {},
                "deleted": false,
                "typeName": "StorageUnitAbdd",
                "hasFile": false,
                "timeStamp": null,
                "operatingDayId": "63136e57-ba05-4fd6-9518-d0a2b379f381",
                "numberSu": "2022-06-14_new_1-2",
                "capacity": 393216,
                "branchId": null,
                "storageDate": "156",
                "savingDate": null,
                "hashSum": "691ac5d6dd97f9d531b722914f276ec1389fbfd2911aef56372a9a7623bac47fc47135a2cc6be1efe77a628eb84630cc9f175ce2e814659eae3668543af57692",
                "hashAlgorithm": "GOST3411-2012-512",
                "savingLocation": "initValue",
                "savingLocationReserv": "initValue",
                "storageUnitStatus": "READY_TO_RECORDING",
                "typeSu": {
                    "elementId": "e806dd0f-e563-460f-8d66-1f2350b6e6f1",
                    "code": "CD",
                    "elementName": "CD/DVD Диск",
                    "shortName": null,
                    "typeName": "StorageUnitTypeAbdd",
                    "creationDate": "2021-11-18T09:36:20.116993",
                    "modifyDate": "2022-04-26T16:28:28.208507",
                    "deleted": true,
                    "creator": "admin",
                    "modifier": "admin",
                    "capacity": 73400320,
                    "isDefault": true,
                    "savingLocation": "initValue",
                    "savingLocationReserv": "initValue"
                },
                "errorMessage": null,
                "isoPresent": true
            },
            {
                "objectId": "7ace4727-1e5e-43ff-8206-19149aace31d",
                "objectName": null,
                "versionId": null,
                "creator": "admin",
                "modifier": "admin",
                "creationDate": "2022-04-08T15:08:06.509687",
                "modifyDate": "2022-05-30T19:04:40.345819",
                "objectState": null,
                "acl": {},
                "deleted": false,
                "typeName": "StorageUnitAbdd",
                "hasFile": false,
                "timeStamp": null,
                "operatingDayId": "63136e57-ba05-4fd6-9518-d0a2b379f381",
                "numberSu": "2",
                "capacity": null,
                "branchId": "aec7e48b-b1e8-4720-8e46-db3d3c1a6398",
                "storageDate": "100",
                "savingDate": "2022-05-20T18:54:02.06887",
                "hashSum": null,
                "hashAlgorithm": null,
                "savingLocation": "initValue2",
                "savingLocationReserv": "initValue2",
                "storageUnitStatus": "RECORDED",
                "typeSu": {
                    "elementId": "2acf6c5d-d35e-4c58-a2d7-394955af2c22",
                    "code": "ABC",
                    "elementName": "elem",
                    "shortName": "short",
                    "typeName": "StorageUnitTypeAbdd",
                    "creationDate": "2021-11-18T09:20:21.173825",
                    "modifyDate": "2022-04-26T16:39:01.626341",
                    "deleted": true,
                    "creator": null,
                    "modifier": "admin",
                    "capacity": 629145600,
                    "isDefault": false,
                    "savingLocation": "initValue",
                    "savingLocationReserv": "initValue"
                },
                "errorMessage": "test",
                "isoPresent": false
            },
            {
                "objectId": "1b48d922-a983-426f-bb9c-bccb16f8dfc7",
                "objectName": "Единица хранения АБДД",
                "versionId": null,
                "creator": "admin",
                "modifier": "system",
                "creationDate": "2022-04-27T10:25:17.556856",
                "modifyDate": "2022-04-29T06:44:48.010755",
                "objectState": null,
                "acl": {},
                "deleted": false,
                "typeName": "StorageUnitAbdd",
                "hasFile": false,
                "timeStamp": null,
                "operatingDayId": "63136e57-ba05-4fd6-9518-d0a2b379f381",
                "numberSu": "123456789033-5",
                "capacity": 479232,
                "branchId": "aec7e48b-b1e8-4720-8e46-db3d3c1a6398",
                "storageDate": "100",
                "savingDate": null,
                "hashSum": "6056049645e1f7f8b90587ac979452c3e22a317b6fde5a71857a1be57fd6d13f778e26f3c781ee89ef3665845f088cb9c3af6ec765c19ebee9b2b8fe829a170e",
                "hashAlgorithm": "GOST3411-2012-512",
                "savingLocation": "initValue",
                "savingLocationReserv": "initValue",
                "storageUnitStatus": "READY_TO_RECORDING",
                "typeSu": {
                    "elementId": "e806dd0f-e563-460f-8d66-1f2350b6e6f1",
                    "code": "CD",
                    "elementName": "CD/DVD Диск",
                    "shortName": null,
                    "typeName": "StorageUnitTypeAbdd",
                    "creationDate": "2021-11-18T09:36:20.116993",
                    "modifyDate": "2022-04-26T16:28:28.208507",
                    "deleted": true,
                    "creator": "admin",
                    "modifier": "admin",
                    "capacity": 73400320,
                    "isDefault": true,
                    "savingLocation": "initValue",
                    "savingLocationReserv": "initValue"
                },
                "errorMessage": null,
                "isoPresent": false
            },
            {
                "objectId": "625377d8-73b6-40c5-aefc-c58ccbbaf09a",
                "objectName": "Единица хранения АБДД",
                "versionId": null,
                "creator": "admin",
                "modifier": "system",
                "creationDate": "2022-04-27T10:25:19.380645",
                "modifyDate": "2022-04-29T10:33:47.495262",
                "objectState": null,
                "acl": {},
                "deleted": false,
                "typeName": "StorageUnitAbdd",
                "hasFile": false,
                "timeStamp": null,
                "operatingDayId": "63136e57-ba05-4fd6-9518-d0a2b379f381",
                "numberSu": "123456789033-9",
                "capacity": 528384,
                "branchId": "aec7e48b-b1e8-4720-8e46-db3d3c1a6398",
                "storageDate": "12",
                "savingDate": null,
                "hashSum": "d0bc973378ba15424e80709ac708154d12c39f4641660765bdc47233fde22f84b94e53fcacc43ecd4b625773fda666c8192fd67a19f560ef64cef6bf064c528c",
                "hashAlgorithm": "GOST3411-2012-512",
                "savingLocation": "initValue",
                "savingLocationReserv": "initValue",
                "storageUnitStatus": "READY_TO_RECORDING",
                "typeSu": {
                    "elementId": "e806dd0f-e563-460f-8d66-1f2350b6e6f1",
                    "code": "CD",
                    "elementName": "CD/DVD Диск",
                    "shortName": null,
                    "typeName": "StorageUnitTypeAbdd",
                    "creationDate": "2021-11-18T09:36:20.116993",
                    "modifyDate": "2022-04-26T16:28:28.208507",
                    "deleted": true,
                    "creator": "admin",
                    "modifier": "admin",
                    "capacity": 73400320,
                    "isDefault": true,
                    "savingLocation": "initValue",
                    "savingLocationReserv": "initValue"
                },
                "errorMessage": null,
                "isoPresent": false
            },
            {
                "objectId": "da77c931-bb1c-496a-999f-f966b795b3e8",
                "objectName": "Единица хранения АБДД",
                "versionId": null,
                "creator": "admin",
                "modifier": "admin",
                "creationDate": "2022-04-27T10:25:15.665651",
                "modifyDate": "2022-04-27T10:25:43.350419",
                "objectState": null,
                "acl": {},
                "deleted": false,
                "typeName": "StorageUnitAbdd",
                "hasFile": false,
                "timeStamp": null,
                "operatingDayId": "63136e57-ba05-4fd6-9518-d0a2b379f381",
                "numberSu": "123456789033-1",
                "capacity": 749568,
                "branchId": "aec7e48b-b1e8-4720-8e46-db3d3c1a6398",
                "storageDate": "156",
                "savingDate": null,
                "hashSum": null,
                "hashAlgorithm": null,
                "savingLocation": "initValue",
                "savingLocationReserv": "initValue",
                "storageUnitStatus": "READY_TO_RECORDING",
                "typeSu": {
                    "elementId": "e806dd0f-e563-460f-8d66-1f2350b6e6f1",
                    "code": "CD",
                    "elementName": "CD/DVD Диск",
                    "shortName": null,
                    "typeName": "StorageUnitTypeAbdd",
                    "creationDate": "2021-11-18T09:36:20.116993",
                    "modifyDate": "2022-04-26T16:28:28.208507",
                    "deleted": true,
                    "creator": "admin",
                    "modifier": "admin",
                    "capacity": 73400320,
                    "isDefault": true,
                    "savingLocation": "initValue",
                    "savingLocationReserv": "initValue"
                },
                "errorMessage": null,
                "isoPresent": false
            },
            {
                "objectId": "fac305be-5145-49fd-8079-9b95bbd581d6",
                "objectName": "Единица хранения АБДД",
                "versionId": null,
                "creator": "admin",
                "modifier": "admin",
                "creationDate": "2022-04-27T10:25:16.112691",
                "modifyDate": "2022-04-27T10:25:47.425959",
                "objectState": null,
                "acl": {},
                "deleted": false,
                "typeName": "StorageUnitAbdd",
                "hasFile": false,
                "timeStamp": null,
                "operatingDayId": "56f7756d-e263-43af-9ffe-9b8d1f3f02cd",
                "numberSu": "123456789033-2",
                "capacity": 464896,
                "branchId": "aec7e48b-b1e8-4720-8e46-db3d3c1a6398",
                "storageDate": "19",
                "savingDate": null,
                "hashSum": null,
                "hashAlgorithm": null,
                "savingLocation": "initValue",
                "savingLocationReserv": "initValue",
                "storageUnitStatus": "READY_TO_RECORDING",
                "typeSu": {
                    "elementId": "e806dd0f-e563-460f-8d66-1f2350b6e6f1",
                    "code": "CD",
                    "elementName": "CD/DVD Диск",
                    "shortName": null,
                    "typeName": "StorageUnitTypeAbdd",
                    "creationDate": "2021-11-18T09:36:20.116993",
                    "modifyDate": "2022-04-26T16:28:28.208507",
                    "deleted": true,
                    "creator": "admin",
                    "modifier": "admin",
                    "capacity": 73400320,
                    "isDefault": true,
                    "savingLocation": "initValue",
                    "savingLocationReserv": "initValue"
                },
                "errorMessage": null,
                "isoPresent": false
            },
            {
                "objectId": "fa1932f5-b352-4247-b3d5-4f10023b3237",
                "objectName": "Единица хранения АБДД",
                "versionId": null,
                "creator": "admin",
                "modifier": "admin",
                "creationDate": "2022-04-27T10:25:16.618232",
                "modifyDate": "2022-04-27T10:26:00.320677",
                "objectState": null,
                "acl": {},
                "deleted": false,
                "typeName": "StorageUnitAbdd",
                "hasFile": false,
                "timeStamp": null,
                "operatingDayId": "56f7756d-e263-43af-9ffe-9b8d1f3f02cd",
                "numberSu": "123456789033-3",
                "capacity": 778240,
                "branchId": "aec7e48b-b1e8-4720-8e46-db3d3c1a6398",
                "storageDate": "12",
                "savingDate": null,
                "hashSum": null,
                "hashAlgorithm": null,
                "savingLocation": "initValue",
                "savingLocationReserv": "initValue",
                "storageUnitStatus": "READY_TO_RECORDING",
                "typeSu": {
                    "elementId": "e806dd0f-e563-460f-8d66-1f2350b6e6f1",
                    "code": "CD",
                    "elementName": "CD/DVD Диск",
                    "shortName": null,
                    "typeName": "StorageUnitTypeAbdd",
                    "creationDate": "2021-11-18T09:36:20.116993",
                    "modifyDate": "2022-04-26T16:28:28.208507",
                    "deleted": true,
                    "creator": "admin",
                    "modifier": "admin",
                    "capacity": 73400320,
                    "isDefault": true,
                    "savingLocation": "initValue",
                    "savingLocationReserv": "initValue"
                },
                "errorMessage": null,
                "isoPresent": false
            },
            {
                "objectId": "c74c3dd2-1a19-4c82-a6ae-2270b3f844a9",
                "objectName": "Единица хранения АБДД",
                "versionId": null,
                "creator": "admin",
                "modifier": "system",
                "creationDate": "2022-04-27T10:25:18.024774",
                "modifyDate": "2022-04-29T10:40:45.48871",
                "objectState": null,
                "acl": {},
                "deleted": false,
                "typeName": "StorageUnitAbdd",
                "hasFile": false,
                "timeStamp": null,
                "operatingDayId": "56f7756d-e263-43af-9ffe-9b8d1f3f02cd",
                "numberSu": "123456789033-6",
                "capacity": 481280,
                "branchId": "aec7e48b-b1e8-4720-8e46-db3d3c1a6398",
                "storageDate": "35",
                "savingDate": null,
                "hashSum": "478f4d0ac0d5f2e96b88113fa6438ef07a004e7ee29f79591594d2f7c6508e4fef53468933ab5863fcb471d8b8d3c3b2b9e121a917840cf36ecb66794481d292",
                "hashAlgorithm": "GOST3411-2012-512",
                "savingLocation": "initValue",
                "savingLocationReserv": "initValue",
                "storageUnitStatus": "READY_TO_RECORDING",
                "typeSu": {
                    "elementId": "e806dd0f-e563-460f-8d66-1f2350b6e6f1",
                    "code": "CD",
                    "elementName": "CD/DVD Диск",
                    "shortName": null,
                    "typeName": "StorageUnitTypeAbdd",
                    "creationDate": "2021-11-18T09:36:20.116993",
                    "modifyDate": "2022-04-26T16:28:28.208507",
                    "deleted": true,
                    "creator": "admin",
                    "modifier": "admin",
                    "capacity": 73400320,
                    "isDefault": true,
                    "savingLocation": "initValue",
                    "savingLocationReserv": "initValue"
                },
                "errorMessage": null,
                "isoPresent": false
            },
            {
                "objectId": "1ee20c16-91d4-44e9-9ef4-72bc3bd7cde6",
                "objectName": "Единица хранения АБДД",
                "versionId": null,
                "creator": "admin",
                "modifier": "admin",
                "creationDate": "2022-04-27T10:25:18.944959",
                "modifyDate": "2022-06-17T13:47:43.513092",
                "objectState": null,
                "acl": {},
                "deleted": false,
                "typeName": "StorageUnitAbdd",
                "hasFile": false,
                "timeStamp": null,
                "operatingDayId": "56f7756d-e263-43af-9ffe-9b8d1f3f02cd",
                "numberSu": "123456789033-8",
                "capacity": 512000,
                "branchId": "aec7e48b-b1e8-4720-8e46-db3d3c1a6398",
                "storageDate": "35",
                "savingDate": null,
                "hashSum": "ccd057b1b979be50f916dbcddddc71ef81afdc7e9da2185ef80dafc287eba786e0636ff3a9b7c7659bb9b3120763b410330e8297915b5e099304db76ec835196",
                "hashAlgorithm": "GOST3411-2012-512",
                "savingLocation": "новое значение15:09",
                "savingLocationReserv": "new value",
                "storageUnitStatus": "RECORDED",
                "typeSu": {
                    "elementId": "e806dd0f-e563-460f-8d66-1f2350b6e6f1",
                    "code": "CD",
                    "elementName": "CD/DVD Диск",
                    "shortName": null,
                    "typeName": "StorageUnitTypeAbdd",
                    "creationDate": "2021-11-18T09:36:20.116993",
                    "modifyDate": "2022-04-26T16:28:28.208507",
                    "deleted": true,
                    "creator": "admin",
                    "modifier": "admin",
                    "capacity": 73400320,
                    "isDefault": true,
                    "savingLocation": "initValue",
                    "savingLocationReserv": "initValue"
                },
                "errorMessage": null,
                "isoPresent": false
            },
            {
                "objectId": "c373a1e4-a90f-4ea0-938d-38021fddcf3d",
                "objectName": "Единица хранения АБДД",
                "versionId": null,
                "creator": "admin",
                "modifier": "system",
                "creationDate": "2022-04-27T10:25:18.490451",
                "modifyDate": "2022-04-29T13:24:42.107155",
                "objectState": null,
                "acl": {},
                "deleted": false,
                "typeName": "StorageUnitAbdd",
                "hasFile": false,
                "timeStamp": null,
                "operatingDayId": "56f7756d-e263-43af-9ffe-9b8d1f3f02cd",
                "numberSu": "123456789033-7",
                "capacity": 458752,
                "branchId": "aec7e48b-b1e8-4720-8e46-db3d3c1a6398",
                "storageDate": "12",
                "savingDate": null,
                "hashSum": "d20d4229c0b50022a8bbd995e2f3f78eb45941e930843b0c798fe5ea83f35488f5407d1665dae30255ed6cf254e792215bdfa558de6bb22deb0ecbc2d3b1cb37",
                "hashAlgorithm": "GOST3411-2012-512",
                "savingLocation": "initValue",
                "savingLocationReserv": "initValue",
                "storageUnitStatus": "RECORDED",
                "typeSu": {
                    "elementId": "e806dd0f-e563-460f-8d66-1f2350b6e6f1",
                    "code": "CD",
                    "elementName": "CD/DVD Диск",
                    "shortName": null,
                    "typeName": "StorageUnitTypeAbdd",
                    "creationDate": "2021-11-18T09:36:20.116993",
                    "modifyDate": "2022-04-26T16:28:28.208507",
                    "deleted": true,
                    "creator": "admin",
                    "modifier": "admin",
                    "capacity": 73400320,
                    "isDefault": true,
                    "savingLocation": "initValue",
                    "savingLocationReserv": "initValue"
                },
                "errorMessage": null,
                "isoPresent": false
            },
            {
                "objectId": "5518d3a3-967b-4dc4-b1a5-66bacd7f91de",
                "objectName": "Единица хранения АБДД",
                "versionId": null,
                "creator": "admin",
                "modifier": "admin",
                "creationDate": "2022-06-17T14:29:59.137936",
                "modifyDate": "2022-06-17T14:31:22.504299",
                "objectState": null,
                "acl": {},
                "deleted": false,
                "typeName": "StorageUnitAbdd",
                "hasFile": false,
                "timeStamp": null,
                "operatingDayId": "56f7756d-e263-43af-9ffe-9b8d1f3f02cd",
                "numberSu": "129-5",
                "capacity": 389120,
                "branchId": null,
                "storageDate": "365",
                "savingDate": "2022-06-17T14:31:22.501718",
                "hashSum": "a838e23d5d518a87128c2b5eff9eb1f5096b63ecad8be249b0bf3d289edad4233f15e08827b728086a63c8b638c5fa9691daf93b64e2bdd881fbe3fe387f81bd",
                "hashAlgorithm": "GOST3411-2012-512",
                "savingLocation": "initValue",
                "savingLocationReserv": "initValue",
                "storageUnitStatus": "RECORDED",
                "typeSu": {
                    "elementId": "e806dd0f-e563-460f-8d66-1f2350b6e6f1",
                    "code": "CD",
                    "elementName": "CD/DVD Диск",
                    "shortName": null,
                    "typeName": "StorageUnitTypeAbdd",
                    "creationDate": "2021-11-18T09:36:20.116993",
                    "modifyDate": "2022-04-26T16:28:28.208507",
                    "deleted": true,
                    "creator": "admin",
                    "modifier": "admin",
                    "capacity": 73400320,
                    "isDefault": true,
                    "savingLocation": "initValue",
                    "savingLocationReserv": "initValue"
                },
                "errorMessage": null,
                "isoPresent": false
            },
            {
                "objectId": "12ee2651-8df8-4eb6-868c-b5d878bb9c95",
                "objectName": "Единица хранения АБДД",
                "versionId": null,
                "creator": "admin",
                "modifier": "admin",
                "creationDate": "2022-06-17T14:29:59.080721",
                "modifyDate": "2022-06-17T14:30:20.0581",
                "objectState": null,
                "acl": {},
                "deleted": false,
                "typeName": "StorageUnitAbdd",
                "hasFile": false,
                "timeStamp": null,
                "operatingDayId": "56f7756d-e263-43af-9ffe-9b8d1f3f02cd",
                "numberSu": "129-1",
                "capacity": 393216,
                "branchId": null,
                "storageDate": "156",
                "savingDate": "2022-06-17T14:30:20.055403",
                "hashSum": "a5940de99ec0083f940bd914023a3ac4ce9a50d69ecf5c145149a67aef7f70b45f2405e5cc32307ff1dae89ef4ea50a9d85b3124ae4256d3e9f614971d876c93",
                "hashAlgorithm": "GOST3411-2012-512",
                "savingLocation": "initValue",
                "savingLocationReserv": "initValue",
                "storageUnitStatus": "RECORDED",
                "typeSu": {
                    "elementId": "e806dd0f-e563-460f-8d66-1f2350b6e6f1",
                    "code": "CD",
                    "elementName": "CD/DVD Диск",
                    "shortName": null,
                    "typeName": "StorageUnitTypeAbdd",
                    "creationDate": "2021-11-18T09:36:20.116993",
                    "modifyDate": "2022-04-26T16:28:28.208507",
                    "deleted": true,
                    "creator": "admin",
                    "modifier": "admin",
                    "capacity": 73400320,
                    "isDefault": true,
                    "savingLocation": "initValue",
                    "savingLocationReserv": "initValue"
                },
                "errorMessage": null,
                "isoPresent": false
            },
            {
                "objectId": "84290236-d66f-4184-a575-1f0cf89d5094",
                "objectName": "Единица хранения АБДД",
                "versionId": null,
                "creator": "admin",
                "modifier": "admin",
                "creationDate": "2022-06-17T14:29:59.091555",
                "modifyDate": "2022-06-17T14:30:22.234417",
                "objectState": null,
                "acl": {},
                "deleted": false,
                "typeName": "StorageUnitAbdd",
                "hasFile": false,
                "timeStamp": null,
                "operatingDayId": "56f7756d-e263-43af-9ffe-9b8d1f3f02cd",
                "numberSu": "129-2",
                "capacity": 395264,
                "branchId": null,
                "storageDate": "19",
                "savingDate": "2022-06-17T14:30:22.231376",
                "hashSum": "fdccfe0088f9ae884ca300c4343684e67cfcc81177ed07258c3bc917049e6d95de87f36212eca74ad2f1a49341ca7179d7bd7c6215c4dfc18e167e1f7f325c40",
                "hashAlgorithm": "GOST3411-2012-512",
                "savingLocation": "initValue",
                "savingLocationReserv": "initValue",
                "storageUnitStatus": "RECORDED",
                "typeSu": {
                    "elementId": "e806dd0f-e563-460f-8d66-1f2350b6e6f1",
                    "code": "CD",
                    "elementName": "CD/DVD Диск",
                    "shortName": null,
                    "typeName": "StorageUnitTypeAbdd",
                    "creationDate": "2021-11-18T09:36:20.116993",
                    "modifyDate": "2022-04-26T16:28:28.208507",
                    "deleted": true,
                    "creator": "admin",
                    "modifier": "admin",
                    "capacity": 73400320,
                    "isDefault": true,
                    "savingLocation": "initValue",
                    "savingLocationReserv": "initValue"
                },
                "errorMessage": null,
                "isoPresent": false
            },
            {
                "objectId": "647427e9-dfc1-43d0-a5d6-cdc4391c52f9",
                "objectName": "Единица хранения АБДД",
                "versionId": null,
                "creator": "admin",
                "modifier": "admin",
                "creationDate": "2022-06-17T14:29:59.101713",
                "modifyDate": "2022-06-17T14:30:24.347006",
                "objectState": null,
                "acl": {},
                "deleted": false,
                "typeName": "StorageUnitAbdd",
                "hasFile": false,
                "timeStamp": null,
                "operatingDayId": "33866f74-3bdc-4a5e-80ba-1843a372657a",
                "numberSu": "129-3",
                "capacity": 395264,
                "branchId": null,
                "storageDate": "12",
                "savingDate": "2022-06-17T14:30:24.344732",
                "hashSum": "81ac988d47a400404034a2421650b4fe282bbd01ca82508a60071982844e1e969eba017b30e5dececf3f826c6525c0b5c489c3fe6e729443d48503254e61150f",
                "hashAlgorithm": "GOST3411-2012-512",
                "savingLocation": "initValue",
                "savingLocationReserv": "initValue",
                "storageUnitStatus": "RECORDED",
                "typeSu": {
                    "elementId": "e806dd0f-e563-460f-8d66-1f2350b6e6f1",
                    "code": "CD",
                    "elementName": "CD/DVD Диск",
                    "shortName": null,
                    "typeName": "StorageUnitTypeAbdd",
                    "creationDate": "2021-11-18T09:36:20.116993",
                    "modifyDate": "2022-04-26T16:28:28.208507",
                    "deleted": true,
                    "creator": "admin",
                    "modifier": "admin",
                    "capacity": 73400320,
                    "isDefault": true,
                    "savingLocation": "initValue",
                    "savingLocationReserv": "initValue"
                },
                "errorMessage": null,
                "isoPresent": false
            },
            {
                "objectId": "3b6c3003-3d0e-4edc-8019-fc451f992706",
                "objectName": "Единица хранения АБДД",
                "versionId": null,
                "creator": "admin",
                "modifier": "admin",
                "creationDate": "2022-06-17T14:29:59.117506",
                "modifyDate": "2022-06-17T14:31:15.966876",
                "objectState": null,
                "acl": {},
                "deleted": false,
                "typeName": "StorageUnitAbdd",
                "hasFile": false,
                "timeStamp": null,
                "operatingDayId": "33866f74-3bdc-4a5e-80ba-1843a372657a",
                "numberSu": "129-4",
                "capacity": 401408,
                "branchId": null,
                "storageDate": "35",
                "savingDate": "2022-06-17T14:31:15.962609",
                "hashSum": "d06e1430c9fbbcaf2e8bb25660d687fcfe582e5ab5914b0fd4bbf158a3c08ebe0a2eba8916d3681753f0e269efedb402629e0c5399890eef781e19a01c783da3",
                "hashAlgorithm": "GOST3411-2012-512",
                "savingLocation": "initValue",
                "savingLocationReserv": "initValue",
                "storageUnitStatus": "RECORDED",
                "typeSu": {
                    "elementId": "e806dd0f-e563-460f-8d66-1f2350b6e6f1",
                    "code": "CD",
                    "elementName": "CD/DVD Диск",
                    "shortName": null,
                    "typeName": "StorageUnitTypeAbdd",
                    "creationDate": "2021-11-18T09:36:20.116993",
                    "modifyDate": "2022-04-26T16:28:28.208507",
                    "deleted": true,
                    "creator": "admin",
                    "modifier": "admin",
                    "capacity": 73400320,
                    "isDefault": true,
                    "savingLocation": "initValue",
                    "savingLocationReserv": "initValue"
                },
                "errorMessage": null,
                "isoPresent": false
            },
            {
                "objectId": "caa54d58-d66e-45bf-aac7-cedae7adb210",
                "objectName": "Единица хранения АБДД",
                "versionId": null,
                "creator": "admin",
                "modifier": "admin",
                "creationDate": "2022-06-17T18:31:41.396126",
                "modifyDate": "2022-06-17T18:31:46.179306",
                "objectState": null,
                "acl": {},
                "deleted": false,
                "typeName": "StorageUnitAbdd",
                "hasFile": false,
                "timeStamp": null,
                "operatingDayId": "9e8a6eec-11e7-40c8-9074-9e167c945ebd",
                "numberSu": "65-1",
                "capacity": 372736,
                "branchId": null,
                "storageDate": "365",
                "savingDate": null,
                "hashSum": "c43815240eaa15d1e247b60a7751f43dabd89cbef33e4e27c58c08309d190522df5b4324612675119ea9d6265d9a2fdad1f5ef86cf8688f2d69924b1aac269e7",
                "hashAlgorithm": "GOST3411-2012-512",
                "savingLocation": "initValue",
                "savingLocationReserv": "initValue",
                "storageUnitStatus": "READY_TO_RECORDING",
                "typeSu": {
                    "elementId": "e806dd0f-e563-460f-8d66-1f2350b6e6f1",
                    "code": "CD",
                    "elementName": "CD/DVD Диск",
                    "shortName": null,
                    "typeName": "StorageUnitTypeAbdd",
                    "creationDate": "2021-11-18T09:36:20.116993",
                    "modifyDate": "2022-04-26T16:28:28.208507",
                    "deleted": true,
                    "creator": "admin",
                    "modifier": "admin",
                    "capacity": 73400320,
                    "isDefault": true,
                    "savingLocation": "initValue",
                    "savingLocationReserv": "initValue"
                },
                "errorMessage": null,
                "isoPresent": false
            },
            {
                "objectId": "abf9a820-42c5-4f27-ad0c-9675e997fb8e",
                "objectName": "Единица хранения АБДД",
                "versionId": null,
                "creator": "admin",
                "modifier": "admin",
                "creationDate": "2022-06-17T18:31:41.735642",
                "modifyDate": "2022-06-17T18:31:48.952472",
                "objectState": null,
                "acl": {},
                "deleted": false,
                "typeName": "StorageUnitAbdd",
                "hasFile": false,
                "timeStamp": null,
                "operatingDayId": "9e8a6eec-11e7-40c8-9074-9e167c945ebd",
                "numberSu": "65-2",
                "capacity": 372736,
                "branchId": null,
                "storageDate": "156",
                "savingDate": null,
                "hashSum": "3dbfb464c9f5e4b4ff6288db6a53319273d1fda9f61be4ba3c00e914ca13f177c426c9e193fcf6615c11b3feb1e47f1a826e42b9ba6e3aa879dec1d3b30550e4",
                "hashAlgorithm": "GOST3411-2012-512",
                "savingLocation": "initValue",
                "savingLocationReserv": "initValue",
                "storageUnitStatus": "READY_TO_RECORDING",
                "typeSu": {
                    "elementId": "e806dd0f-e563-460f-8d66-1f2350b6e6f1",
                    "code": "CD",
                    "elementName": "CD/DVD Диск",
                    "shortName": null,
                    "typeName": "StorageUnitTypeAbdd",
                    "creationDate": "2021-11-18T09:36:20.116993",
                    "modifyDate": "2022-04-26T16:28:28.208507",
                    "deleted": true,
                    "creator": "admin",
                    "modifier": "admin",
                    "capacity": 73400320,
                    "isDefault": true,
                    "savingLocation": "initValue",
                    "savingLocationReserv": "initValue"
                },
                "errorMessage": null,
                "isoPresent": false
            },
            {
                "objectId": "ed6d90d9-963c-43df-ba99-ad94add4e334",
                "objectName": null,
                "versionId": null,
                "creator": "admin",
                "modifier": "system",
                "creationDate": "2022-04-08T15:08:06.825986",
                "modifyDate": "2022-06-18T21:36:43.500323",
                "objectState": null,
                "acl": {},
                "deleted": false,
                "typeName": "StorageUnitAbdd",
                "hasFile": false,
                "timeStamp": null,
                "operatingDayId": "730bfab3-f3ca-4911-86b0-9ae9048af842",
                "numberSu": "1",
                "capacity": 442368,
                "branchId": "aec7e48b-b1e8-4720-8e46-db3d3c1a6398",
                "storageDate": "100",
                "savingDate": null,
                "hashSum": "6bbd45320ce0e79afb7df721e34d6ae911929cb8fb0f1de203325ee6848717e12babb1daf0647219a86c17a12af6da423ce4714f02354fe34629ca019f46ec62",
                "hashAlgorithm": "GOST3411-2012-512",
                "savingLocation": "initValue",
                "savingLocationReserv": "initValue",
                "storageUnitStatus": "READY_TO_RECORDING",
                "typeSu": {
                    "elementId": "2acf6c5d-d35e-4c58-a2d7-394955af2c22",
                    "code": "ABC",
                    "elementName": "elem",
                    "shortName": "short",
                    "typeName": "StorageUnitTypeAbdd",
                    "creationDate": "2021-11-18T09:20:21.173825",
                    "modifyDate": "2022-04-26T16:39:01.626341",
                    "deleted": true,
                    "creator": null,
                    "modifier": "admin",
                    "capacity": 629145600,
                    "isDefault": false,
                    "savingLocation": "initValue",
                    "savingLocationReserv": "initValue"
                },
                "errorMessage": null,
                "isoPresent": false
            },
            {
                "objectId": "eb35b23d-eead-4996-9258-af6f65ab5a56",
                "objectName": "Единица хранения АБДД",
                "versionId": null,
                "creator": "admin",
                "modifier": "admin",
                "creationDate": "2022-06-17T18:31:42.413047",
                "modifyDate": "2022-06-17T18:31:51.611815",
                "objectState": null,
                "acl": {},
                "deleted": false,
                "typeName": "StorageUnitAbdd",
                "hasFile": false,
                "timeStamp": null,
                "operatingDayId": "9e8a6eec-11e7-40c8-9074-9e167c945ebd",
                "numberSu": "65-4",
                "capacity": 372736,
                "branchId": null,
                "storageDate": "12",
                "savingDate": null,
                "hashSum": "a14a6789d625b0d4c1f9d2a4bf4cc965140888ce3a1efdc578b4247ec37f6d98dc0c1f2dfd150ffad337c2bd029bc3f95f177121edfc45915ff13e503d41bf83",
                "hashAlgorithm": "GOST3411-2012-512",
                "savingLocation": "initValue",
                "savingLocationReserv": "initValue",
                "storageUnitStatus": "READY_TO_RECORDING",
                "typeSu": {
                    "elementId": "e806dd0f-e563-460f-8d66-1f2350b6e6f1",
                    "code": "CD",
                    "elementName": "CD/DVD Диск",
                    "shortName": null,
                    "typeName": "StorageUnitTypeAbdd",
                    "creationDate": "2021-11-18T09:36:20.116993",
                    "modifyDate": "2022-04-26T16:28:28.208507",
                    "deleted": true,
                    "creator": "admin",
                    "modifier": "admin",
                    "capacity": 73400320,
                    "isDefault": true,
                    "savingLocation": "initValue",
                    "savingLocationReserv": "initValue"
                },
                "errorMessage": null,
                "isoPresent": false
            },
            {
                "objectId": "fb619cb1-a4c4-42aa-80a2-ca89527239ce",
                "objectName": "Единица хранения АБДД",
                "versionId": null,
                "creator": "admin",
                "modifier": "admin",
                "creationDate": "2022-06-17T18:31:42.748768",
                "modifyDate": "2022-06-17T18:31:54.218381",
                "objectState": null,
                "acl": {},
                "deleted": false,
                "typeName": "StorageUnitAbdd",
                "hasFile": false,
                "timeStamp": null,
                "operatingDayId": "9e8a6eec-11e7-40c8-9074-9e167c945ebd",
                "numberSu": "65-5",
                "capacity": 372736,
                "branchId": null,
                "storageDate": "35",
                "savingDate": null,
                "hashSum": "23d6cacbaa269fc944532b6df41e745394eeb71672a41a8071799e4aeca3bf291b591f524cfd8b2c14f2553a2c109c74f8477bda5927b5b8971e58dead47c0c6",
                "hashAlgorithm": "GOST3411-2012-512",
                "savingLocation": "initValue",
                "savingLocationReserv": "initValue",
                "storageUnitStatus": "READY_TO_RECORDING",
                "typeSu": {
                    "elementId": "e806dd0f-e563-460f-8d66-1f2350b6e6f1",
                    "code": "CD",
                    "elementName": "CD/DVD Диск",
                    "shortName": null,
                    "typeName": "StorageUnitTypeAbdd",
                    "creationDate": "2021-11-18T09:36:20.116993",
                    "modifyDate": "2022-04-26T16:28:28.208507",
                    "deleted": true,
                    "creator": "admin",
                    "modifier": "admin",
                    "capacity": 73400320,
                    "isDefault": true,
                    "savingLocation": "initValue",
                    "savingLocationReserv": "initValue"
                },
                "errorMessage": null,
                "isoPresent": false
            },
            {
                "objectId": "3fbf27b6-9d5c-470a-80fa-1f47eae1b9b7",
                "objectName": "Единица хранения АБДД",
                "versionId": null,
                "creator": "admin",
                "modifier": "admin",
                "creationDate": "2022-06-17T18:31:42.073752",
                "modifyDate": "2022-06-17T18:31:56.786408",
                "objectState": null,
                "acl": {},
                "deleted": false,
                "typeName": "StorageUnitAbdd",
                "hasFile": false,
                "timeStamp": null,
                "operatingDayId": "9e8a6eec-11e7-40c8-9074-9e167c945ebd",
                "numberSu": "65-3",
                "capacity": 372736,
                "branchId": null,
                "storageDate": "19",
                "savingDate": null,
                "hashSum": "c80ce046b989c38f168455fb4ed6b6a82044f80b3c88b31465521e7b3fc803de2bb944169fae44a1a0c828a54bc36212a83a99645b2af47bb875db53c14f13f3",
                "hashAlgorithm": "GOST3411-2012-512",
                "savingLocation": "initValue",
                "savingLocationReserv": "initValue",
                "storageUnitStatus": "READY_TO_RECORDING",
                "typeSu": {
                    "elementId": "e806dd0f-e563-460f-8d66-1f2350b6e6f1",
                    "code": "CD",
                    "elementName": "CD/DVD Диск",
                    "shortName": null,
                    "typeName": "StorageUnitTypeAbdd",
                    "creationDate": "2021-11-18T09:36:20.116993",
                    "modifyDate": "2022-04-26T16:28:28.208507",
                    "deleted": true,
                    "creator": "admin",
                    "modifier": "admin",
                    "capacity": 73400320,
                    "isDefault": true,
                    "savingLocation": "initValue",
                    "savingLocationReserv": "initValue"
                },
                "errorMessage": null,
                "isoPresent": false
            },
            {
                "objectId": "215d6ba0-5803-4a7d-9fa4-0f39786fefc6",
                "objectName": "Единица хранения АБДД",
                "versionId": null,
                "creator": "admin",
                "modifier": "system",
                "creationDate": "2022-06-23T12:58:35.83056",
                "modifyDate": "2022-07-11T20:31:17.647888",
                "objectState": null,
                "acl": {},
                "deleted": false,
                "typeName": "StorageUnitAbdd",
                "hasFile": false,
                "timeStamp": null,
                "operatingDayId": "2a30281b-2abd-44d9-bbbc-149ee7b8bfd4",
                "numberSu": "2022-06-14_new_1-1",
                "capacity": 389120,
                "branchId": null,
                "storageDate": "365",
                "savingDate": null,
                "hashSum": "738a7fa35a90e7798bfb8b1f600515d147c11a5d1760eb3b406e320ea0eb25bddbc174662195c7f5ea6f65bee21ed724c359fd60f8094b1730031ce2ed4b79e5",
                "hashAlgorithm": "GOST3411-2012-512",
                "savingLocation": "initValue",
                "savingLocationReserv": "initValue",
                "storageUnitStatus": "READY_TO_RECORDING",
                "typeSu": {
                    "elementId": "e806dd0f-e563-460f-8d66-1f2350b6e6f1",
                    "code": "CD",
                    "elementName": "CD/DVD Диск",
                    "shortName": null,
                    "typeName": "StorageUnitTypeAbdd",
                    "creationDate": "2021-11-18T09:36:20.116993",
                    "modifyDate": "2022-04-26T16:28:28.208507",
                    "deleted": true,
                    "creator": "admin",
                    "modifier": "admin",
                    "capacity": 73400320,
                    "isDefault": true,
                    "savingLocation": "initValue",
                    "savingLocationReserv": "initValue"
                },
                "errorMessage": null,
                "isoPresent": true
            },
            {
                "objectId": "e8d786d6-afd8-4be5-9dad-bbdee6f80b40",
                "objectName": "Единица хранения АБДД",
                "versionId": null,
                "creator": "admin",
                "modifier": "admin",
                "creationDate": "2022-06-23T13:31:24.039824",
                "modifyDate": "2022-06-23T13:32:05.558707",
                "objectState": null,
                "acl": {},
                "deleted": false,
                "typeName": "StorageUnitAbdd",
                "hasFile": false,
                "timeStamp": null,
                "operatingDayId": "667ee267-894e-43f9-a49c-7d43ccc28dda",
                "numberSu": "2022-02-25-1",
                "capacity": 409600,
                "branchId": null,
                "storageDate": "156",
                "savingDate": null,
                "hashSum": "86caaece73470dceb6edfc605ed42ad644255c0fc10bef27c56248ffdb7a5141a5aa3312e3399d69ee527820a7fbcc6909744e7659eaf35b504043d869bc904e",
                "hashAlgorithm": "GOST3411-2012-512",
                "savingLocation": "initValue",
                "savingLocationReserv": "initValue",
                "storageUnitStatus": "READY_TO_RECORDING",
                "typeSu": {
                    "elementId": "e806dd0f-e563-460f-8d66-1f2350b6e6f1",
                    "code": "CD",
                    "elementName": "CD/DVD Диск",
                    "shortName": null,
                    "typeName": "StorageUnitTypeAbdd",
                    "creationDate": "2021-11-18T09:36:20.116993",
                    "modifyDate": "2022-04-26T16:28:28.208507",
                    "deleted": true,
                    "creator": "admin",
                    "modifier": "admin",
                    "capacity": 73400320,
                    "isDefault": true,
                    "savingLocation": "initValue",
                    "savingLocationReserv": "initValue"
                },
                "errorMessage": null,
                "isoPresent": false
            },
            {
                "objectId": "49c2e139-bfab-4db2-9ecf-d80f4f53817f",
                "objectName": "Единица хранения АБДД",
                "versionId": null,
                "creator": "admin",
                "modifier": "admin",
                "creationDate": "2022-07-04T12:48:32.027888",
                "modifyDate": "2022-07-04T12:48:32.63692",
                "objectState": null,
                "acl": {},
                "deleted": false,
                "typeName": "StorageUnitAbdd",
                "hasFile": false,
                "timeStamp": null,
                "operatingDayId": "5d6414f2-6890-476a-8415-aac02dce8fd3",
                "numberSu": "431-2",
                "capacity": 395264,
                "branchId": null,
                "storageDate": "19",
                "savingDate": null,
                "hashSum": "2828ad961fb4a785570388d7336ce754e63e8a5d85bf0f519425259997b880dff9d36adcbf0d2f9afb23dcd89b31e283f51b17fce7bd6c90d499a49d33bb8649",
                "hashAlgorithm": "GOST3411-2012-512",
                "savingLocation": "initValue",
                "savingLocationReserv": "initValue",
                "storageUnitStatus": "READY_TO_RECORDING",
                "typeSu": {
                    "elementId": "e806dd0f-e563-460f-8d66-1f2350b6e6f1",
                    "code": "CD",
                    "elementName": "CD/DVD Диск",
                    "shortName": null,
                    "typeName": "StorageUnitTypeAbdd",
                    "creationDate": "2021-11-18T09:36:20.116993",
                    "modifyDate": "2022-04-26T16:28:28.208507",
                    "deleted": true,
                    "creator": "admin",
                    "modifier": "admin",
                    "capacity": 73400320,
                    "isDefault": true,
                    "savingLocation": "initValue",
                    "savingLocationReserv": "initValue"
                },
                "errorMessage": null,
                "isoPresent": true
            },
            {
                "objectId": "da18c600-db1f-437b-8f3b-4efcccd8996c",
                "objectName": "Единица хранения АБДД",
                "versionId": null,
                "creator": "admin",
                "modifier": "admin",
                "creationDate": "2022-07-04T12:48:32.036643",
                "modifyDate": "2022-07-04T12:48:32.734053",
                "objectState": null,
                "acl": {},
                "deleted": false,
                "typeName": "StorageUnitAbdd",
                "hasFile": false,
                "timeStamp": null,
                "operatingDayId": "5d6414f2-6890-476a-8415-aac02dce8fd3",
                "numberSu": "431-3",
                "capacity": 423936,
                "branchId": null,
                "storageDate": "12",
                "savingDate": null,
                "hashSum": "40097535dfa3cf88addd3f703ac5f5a9fbe8be0400ba567fa1a56ce1ede4f4d847d9b10cef150fbf954b22169929becaa1e913b7f03fdd11e0b026796e901cd7",
                "hashAlgorithm": "GOST3411-2012-512",
                "savingLocation": "initValue",
                "savingLocationReserv": "initValue",
                "storageUnitStatus": "READY_TO_RECORDING",
                "typeSu": {
                    "elementId": "e806dd0f-e563-460f-8d66-1f2350b6e6f1",
                    "code": "CD",
                    "elementName": "CD/DVD Диск",
                    "shortName": null,
                    "typeName": "StorageUnitTypeAbdd",
                    "creationDate": "2021-11-18T09:36:20.116993",
                    "modifyDate": "2022-04-26T16:28:28.208507",
                    "deleted": true,
                    "creator": "admin",
                    "modifier": "admin",
                    "capacity": 73400320,
                    "isDefault": true,
                    "savingLocation": "initValue",
                    "savingLocationReserv": "initValue"
                },
                "errorMessage": null,
                "isoPresent": true
            },
            {
                "objectId": "c15f5a7e-4665-41af-832b-d859c84def50",
                "objectName": "Единица хранения АБДД",
                "versionId": null,
                "creator": "admin",
                "modifier": "admin",
                "creationDate": "2022-07-04T12:48:31.988416",
                "modifyDate": "2022-07-04T12:48:32.555866",
                "objectState": null,
                "acl": {},
                "deleted": false,
                "typeName": "StorageUnitAbdd",
                "hasFile": false,
                "timeStamp": null,
                "operatingDayId": "5d6414f2-6890-476a-8415-aac02dce8fd3",
                "numberSu": "431-1",
                "capacity": 393216,
                "branchId": null,
                "storageDate": "156",
                "savingDate": null,
                "hashSum": "ffca2041ad0fde5693c366bc744ca1461dfb3ee3a7d7c59e21e150c530eab972558cf7128b9a0ae672ffc88aa2f9206d2c96ef545ab8fb57b1730c7d942a90e0",
                "hashAlgorithm": "GOST3411-2012-512",
                "savingLocation": "initValue",
                "savingLocationReserv": "initValue",
                "storageUnitStatus": "READY_TO_RECORDING",
                "typeSu": {
                    "elementId": "e806dd0f-e563-460f-8d66-1f2350b6e6f1",
                    "code": "CD",
                    "elementName": "CD/DVD Диск",
                    "shortName": null,
                    "typeName": "StorageUnitTypeAbdd",
                    "creationDate": "2021-11-18T09:36:20.116993",
                    "modifyDate": "2022-04-26T16:28:28.208507",
                    "deleted": true,
                    "creator": "admin",
                    "modifier": "admin",
                    "capacity": 73400320,
                    "isDefault": true,
                    "savingLocation": "initValue",
                    "savingLocationReserv": "initValue"
                },
                "errorMessage": null,
                "isoPresent": true
            },
            {
                "objectId": "319901c4-9ac3-4e69-abe5-32004464f6da",
                "objectName": "Единица хранения АБДД",
                "versionId": null,
                "creator": "admin",
                "modifier": "admin",
                "creationDate": "2022-07-04T12:48:32.046652",
                "modifyDate": "2022-07-04T12:48:32.838807",
                "objectState": null,
                "acl": {},
                "deleted": false,
                "typeName": "StorageUnitAbdd",
                "hasFile": false,
                "timeStamp": null,
                "operatingDayId": "5d6414f2-6890-476a-8415-aac02dce8fd3",
                "numberSu": "431-4",
                "capacity": 389120,
                "branchId": null,
                "storageDate": "365",
                "savingDate": null,
                "hashSum": "2e55a547c984e64a85e22363485eb65ed2c7a5890e0bdc78e73c2a918e275e2b13f2b53c9cf1d83021e7243022a64836b1a86aeadc4458bdef6597cedf6eeaae",
                "hashAlgorithm": "GOST3411-2012-512",
                "savingLocation": "initValue",
                "savingLocationReserv": "initValue",
                "storageUnitStatus": "READY_TO_RECORDING",
                "typeSu": {
                    "elementId": "e806dd0f-e563-460f-8d66-1f2350b6e6f1",
                    "code": "CD",
                    "elementName": "CD/DVD Диск",
                    "shortName": null,
                    "typeName": "StorageUnitTypeAbdd",
                    "creationDate": "2021-11-18T09:36:20.116993",
                    "modifyDate": "2022-04-26T16:28:28.208507",
                    "deleted": true,
                    "creator": "admin",
                    "modifier": "admin",
                    "capacity": 73400320,
                    "isDefault": true,
                    "savingLocation": "initValue",
                    "savingLocationReserv": "initValue"
                },
                "errorMessage": null,
                "isoPresent": true
            },
            {
                "objectId": "938c4a27-5c99-4038-9f83-93cad247b07d",
                "objectName": "Единица хранения АБДД",
                "versionId": null,
                "creator": "admin",
                "modifier": "system",
                "creationDate": "2022-04-27T10:25:17.086882",
                "modifyDate": "2022-07-08T15:09:55.994922",
                "objectState": null,
                "acl": {},
                "deleted": false,
                "typeName": "StorageUnitAbdd",
                "hasFile": false,
                "timeStamp": null,
                "operatingDayId": "4ab9070d-f445-4cab-897f-27cf655a1ce5",
                "numberSu": "123456789033-4",
                "capacity": 557056,
                "branchId": "aec7e48b-b1e8-4720-8e46-db3d3c1a6398",
                "storageDate": "15",
                "savingDate": null,
                "hashSum": "c078dcfde027d832066d6af7d5febd5849feda7c31caeb150ce2f12831e2a9530ab707852a4b0e9521514526dec846b57497139a2959b1d8800df5d8cb647f47",
                "hashAlgorithm": "GOST3411-2012-512",
                "savingLocation": "initValue",
                "savingLocationReserv": "initValue",
                "storageUnitStatus": "READY_TO_RECORDING",
                "typeSu": {
                    "elementId": "e806dd0f-e563-460f-8d66-1f2350b6e6f1",
                    "code": "CD",
                    "elementName": "CD/DVD Диск",
                    "shortName": null,
                    "typeName": "StorageUnitTypeAbdd",
                    "creationDate": "2021-11-18T09:36:20.116993",
                    "modifyDate": "2022-04-26T16:28:28.208507",
                    "deleted": true,
                    "creator": "admin",
                    "modifier": "admin",
                    "capacity": 73400320,
                    "isDefault": true,
                    "savingLocation": "initValue",
                    "savingLocationReserv": "initValue"
                },
                "errorMessage": null,
                "isoPresent": true
            }
        ],
        "count": 28
    },
    "errorCode": null,
    "errorMessage": null,
    "errorStack": null
}
